bytedassertgentools/__init__.py
bytedassertgentools-0.0.1.dist-info/METADATA
bytedassertgentools-0.0.1.dist-info/WHEEL
bytedassertgentools-0.0.1.dist-info/top_level.txt
bytedassertgentools-0.0.1.dist-info/RECORD
